talked/__init__.py
talked/__main__.py
talked/ffmpeg.py
talked/main.py
talked/recorder.py
talked/static/custom_css.js
talked-0.5.0.dist-info/LICENSE
talked-0.5.0.dist-info/METADATA
talked-0.5.0.dist-info/WHEEL
talked-0.5.0.dist-info/entry_points.txt
talked-0.5.0.dist-info/RECORD
