Metadata-Version: 2.1
Name: talked
Version: 0.5.0
Summary: Call recording for Nextcloud Talk
Home-page: https://github.com/MetaProvide/talked
License: AGPL-3.0-or-later
Author: Magnus Walbeck
Author-email: mw@mwalbeck.org
Requires-Python: >=3.7,<4.0
Classifier: License :: OSI Approved :: GNU Affero General Public License v3 or later (AGPLv3+)
Classifier: Programming Language :: Python :: 3
Classifier: Programming Language :: Python :: 3.7
Classifier: Programming Language :: Python :: 3.8
Classifier: Programming Language :: Python :: 3.9
Classifier: Programming Language :: Python :: 3.10
Classifier: Programming Language :: Python :: 3.11
Requires-Dist: Flask (>=1.1.2,<3)
Requires-Dist: PyVirtualDisplay (>=0.2.1,<3)
Requires-Dist: selenium (>=3.141.0,<5)
Requires-Dist: tomlkit (>=0.6.0,<0.8)
Project-URL: Repository, https://github.com/MetaProvide/talked
